{
  "source_csv": "/Users/shamiraventurini/PycharmProjects/Geometry-of-Syntax/corpora/transitive/CORE_transitive_constrained_counterbalanced.csv",
  "output_csv": "/Users/shamiraventurini/PycharmProjects/Geometry-of-Syntax/corpora/transitive/CORE_transitive_constrained_counterbalanced_lexically_controlled.csv",
  "summary_json": "/Users/shamiraventurini/PycharmProjects/Geometry-of-Syntax/corpora/transitive/CORE_transitive_constrained_counterbalanced_lexically_controlled_summary.json",
  "seed": 13,
  "constraints": [
    "Prime and target must not share the active-form verb.",
    "Prime and target must not share either noun.",
    "Prime and target passive auxiliaries must be opposite (is/was mismatch)."
  ],
  "audit": {
    "row_count": 2080,
    "prime_source_row_indices_preview": [
      1801,
      210,
      710,
      1311,
      528,
      281,
      820,
      1217,
      1720,
      183,
      103,
      1022,
      893,
      594,
      1872,
      1435,
      625,
      1646,
      452,
      1140,
      353,
      1656,
      887,
      683,
      733
    ],
    "same_verb_rows": 0,
    "shared_noun_rows": 0,
    "shared_aux_rows": 0,
    "same_verb_rate": 0.0,
    "shared_noun_rate": 0.0,
    "shared_aux_rate": 0.0
  },
  "notes": [
    "Each output row keeps the original target ta/tp and replaces the prime pa/pp with a matched row from the source corpus.",
    "The original constrained corpus is retained separately as the lexical-overlap comparison condition."
  ]
}
